gene_thesaurus/__init__.py
gene_thesaurus/gene_thesaurus.py
gene_thesaurus/hgnc_translation_provider.py
gene_thesaurus/ncbi_translation_provider.py
gene_thesaurus/translation_provider.py
gene_thesaurus-3.1.0.dist-info/LICENSE
gene_thesaurus-3.1.0.dist-info/METADATA
gene_thesaurus-3.1.0.dist-info/WHEEL
gene_thesaurus-3.1.0.dist-info/top_level.txt
gene_thesaurus-3.1.0.dist-info/RECORD
