Metadata-Version: 2.1
Name: gene-thesaurus
Version: 3.1.0
Summary: GeneThesaurus is a Python package that translates gene aliases and old gene symbols to the current HGNC standard gene symbols.
Author-email: Mariya Lysenkova Wiklander <mariya.lysenkova@medsci.uu.se>
License: MIT License
Project-URL: Homepage, https://github.com/Molmed/gene-thesaurus
Keywords: genomics,gene,HGNC
Classifier: License :: OSI Approved :: MIT License
Classifier: Programming Language :: Python
Classifier: Programming Language :: Python :: 3
Requires-Python: >=3.8
License-File: LICENSE
Requires-Dist: requests>=2.31.0
Requires-Dist: pandas>=2.0.0
Provides-Extra: dev
Requires-Dist: pytest; extra == "dev"
Requires-Dist: bumpver; extra == "dev"
Requires-Dist: pip-tools; extra == "dev"
Requires-Dist: freezegun; extra == "dev"
Requires-Dist: flake8; extra == "dev"
